examples/wireguard/__init__.py
examples/wireguard/main.py
noise/__init__.py
noise/connection.py
noise/constants.py
noise/exceptions.py
noise/noise_protocol.py
noise/patterns.py
noise/state.py
noise/backends/__init__.py
noise/backends/noise_backend.py
noise/backends/default/__init__.py
noise/backends/default/backend.py
noise/backends/default/ciphers.py
noise/backends/default/diffie_hellmans.py
noise/backends/default/hashes.py
noise/backends/default/keypairs.py
noise/backends/experimental/__init__.py
noise/backends/experimental/backend.py
noise/functions/__init__.py
noise/functions/cipher.py
noise/functions/dh.py
noise/functions/hash.py
noise/functions/keypair.py
noise/functions/patterns.py
noiseprotocol-0.3.1.dist-info/LICENSE
noiseprotocol-0.3.1.dist-info/METADATA
noiseprotocol-0.3.1.dist-info/WHEEL
noiseprotocol-0.3.1.dist-info/top_level.txt
noiseprotocol-0.3.1.dist-info/RECORD
