Metadata-Version: 1.2
Name: noiseprotocol
Version: 0.3.1
Summary: Implementation of Noise Protocol Framework
Home-page: https://github.com/plizonczyk/noiseprotocol
Author: Piotr Lizonczyk
Author-email: plizonczyk.public@gmail.com
License: MIT
Keywords: cryptography noiseprotocol noise security
Platform: UNKNOWN
Classifier: Development Status :: 3 - Alpha
Classifier: Intended Audience :: Developers
Classifier: Topic :: Security :: Cryptography
Classifier: License :: OSI Approved :: MIT License
Classifier: Programming Language :: Python :: 3
Classifier: Programming Language :: Python :: 3.5
Classifier: Programming Language :: Python :: 3.6
Classifier: Programming Language :: Python :: 3.7
Classifier: Programming Language :: Python :: 3.8
Classifier: Operating System :: MacOS :: MacOS X
Classifier: Operating System :: Microsoft :: Windows
Classifier: Operating System :: POSIX :: Linux
Requires-Python: ~=3.5
